
{
  "format_version": "1.10.0",
  "minecraft:client_entity": {
    "description": {
      "identifier": "arkcraft:nanuqsaurus",
      "materials": {
        "default": "cow"
      },            
      "textures": {
        "default": "textures/entity/nanuqsaurus"
      },
      "geometry": {
        "default": "geometry.teratophoneus"
      },
      "animations": {
        "walk": "animation.teratophoneus.move",
      "default":
        "animation.teratophoneus_default"
      },
      "scripts": {
        "animate": [
       "default",
          { "walk": "query.modified_move_speed" }
        ]
      },
      "render_controllers": [ "controller.render.teratophoneus" ],
      "spawn_egg": {
         "base_color": "#EEEEEE",
        "overlay_color": "#0"
      }
    }
  }
}