{
	"format_version": "1.10.0",
	"geometry.water_bug": {
		"texturewidth": 64,
		"textureheight": 64,
		"visible_bounds_width": 3,
		"visible_bounds_height": 2,
		"visible_bounds_offset": [0, 1, 0],
		"bones": [
			{
				"name": "all",
				"pivot": [0, 4, 4],
				"rotation": [0, 180, 0]
			},
			{
				"name": "bone4",
				"parent": "all",
				"pivot": [0, 6.344, 6.344],
				"cubes": [
					{"origin": [-2.2204, 2.23009, 8.04251], "size": [3.172, 4.2822, 8.137], "uv": [44, 0]},
					{"origin": [-1.586, 16.2122, -0.0618], "size": [1.586, 1.586, 1.586], "uv": [60, 9]},
					{"origin": [-1.586, 14.309, 3.586], "size": [1.586, 1.586, 1.586], "uv": [60, 16]},
					{"origin": [-1.586, 12.2472, 6.758], "size": [1.586, 1.586, 1.586], "uv": [60, 25]}
				]
			},
			{
				"name": "bone3",
				"parent": "bone4",
				"pivot": [0, 6.344, 8.4058]
			},
			{
				"name": "leg6",
				"parent": "bone3",
				"pivot": [0, 6.344, 16.653],
				"rotation": [0, 0, -6]
			},
			{
				"name": "bone11",
				"parent": "leg6",
				"pivot": [0, 6.344, 0],
				"rotation": [0, 0, -5],
				"cubes": [
					{"origin": [-0.94752, 3.76094, 13.9918], "size": [8.93, 1.1102, 1.1102], "uv": [48, 43]}
				]
			},
			{
				"name": "bone13",
				"parent": "leg6",
				"pivot": [0, 6.344, 8.4058],
				"rotation": [0, 0, 45],
				"cubes": [
					{"origin": [5.68584, 10.60042, 13.9918], "size": [10.4676, 1.1102, 1.1102], "uv": [42, 48]}
				]
			},
			{
				"name": "leg7",
				"parent": "bone3",
				"pivot": [-1.586, 6.344, 16.653],
				"rotation": [0, 0, 6]
			},
			{
				"name": "bone15",
				"parent": "leg7",
				"pivot": [-1.586, 6.344, 16.653],
				"rotation": [0, 0, 5],
				"cubes": [
					{"origin": [-9.37344, 3.46795, 13.9918], "size": [8.93, 1.1102, 1.1102], "uv": [48, 49]}
				]
			},
			{
				"name": "bone16",
				"parent": "leg7",
				"pivot": [0, 6.344, 8.4058],
				"rotation": [0, 0, -47],
				"cubes": [
					{"origin": [-16.16773, 11.47442, 13.9918], "size": [9.516, 1.1102, 1.1102], "uv": [44, 47]}
				]
			},
			{
				"name": "bone2",
				"parent": "bone4",
				"pivot": [0, 6.344, 5.551]
			},
			{
				"name": "leg2",
				"parent": "bone2",
				"pivot": [0, 6.344, 13.7982],
				"rotation": [0, 10, -4]
			},
			{
				"name": "bone8",
				"parent": "leg2",
				"pivot": [0, 6.344, 5.551],
				"rotation": [0, 0, -15],
				"cubes": [
					{"origin": [-1.94752, 3.76094, 11.137], "size": [13.102, 1.1102, 1.1102], "uv": [40, 53]}
				]
			},
			{
				"name": "bone10",
				"parent": "leg2",
				"pivot": [0, 6.344, 5.551],
				"rotation": [0, 0, 50],
				"cubes": [
					{"origin": [6.16326, 14.33253, 11.137], "size": [11.102, 1.1102, 1.1102], "uv": [40, 51]}
				]
			},
			{
				"name": "leg3",
				"parent": "bone2",
				"pivot": [-1.586, 6.344, 13.7982],
				"rotation": [0, -10, 4]
			},
			{
				"name": "bone18",
				"parent": "leg3",
				"pivot": [0, 6.344, 5.551],
				"rotation": [0, 0, 15],
				"cubes": [
					{"origin": [-12.53941, 3.32972, 11.137], "size": [14.102, 1.1102, 1.1102], "uv": [40, 61]}
				]
			},
			{
				"name": "bone19",
				"parent": "leg3",
				"pivot": [0, 6.344, 5.551],
				"rotation": [0, 0, -50],
				"cubes": [
					{"origin": [-18.28989, 15.44586, 11.137], "size": [11.102, 1.1102, 1.1102], "uv": [40, 55]}
				]
			},
			{
				"name": "leg1",
				"parent": "bone4",
				"pivot": [-1.586, 6.8198, 13.0052],
				"rotation": [10, 135, 3]
			},
			{
				"name": "bone21",
				"parent": "leg1",
				"pivot": [17.44886, 3.17564, 6.39536],
				"rotation": [70, -45, -100],
				"cubes": [
					{"origin": [25.3075, 5.61879, 10.20337], "size": [1.586, 1.586, 13.688], "uv": [38, 51]}
				]
			},
			{
				"name": "bone20",
				"parent": "leg1",
				"pivot": [17.44886, 3.17564, 6.39536],
				"rotation": [70, -45, -20],
				"cubes": [
					{"origin": [17.94106, -0.50052, 4.45527], "size": [1.2688, 1, 12.0536], "uv": [38, 51]}
				]
			},
			{
				"name": "leg0",
				"parent": "bone4",
				"pivot": [0, 6.344, 12.688],
				"rotation": [0, 18, 0]
			},
			{
				"name": "bone6",
				"parent": "leg0",
				"pivot": [0, 6.344, 7.93],
				"rotation": [70, -45, -100],
				"cubes": [
					{"origin": [-0.12481, 1.68397, -3.9704], "size": [1.586, 1.586, 13.688], "uv": [38, 48]}
				]
			},
			{
				"name": "bone7",
				"parent": "leg0",
				"pivot": [0, 6.344, 7.93],
				"rotation": [70, -45, -20],
				"cubes": [
					{"origin": [7.7312, 13.27703, -7.62794], "size": [1.2688, 1, 12.0536], "uv": [38, 52]}
				]
			},
			{
				"name": "bone22",
				"parent": "bone4",
				"pivot": [0, 6.344, 6.344],
				"rotation": [11, 0, 0],
				"cubes": [
					{"origin": [-2.2204, -0.55536, 15.24826], "size": [3.172, 4.758, 2.0618], "uv": [54, 4]}
				]
			},
			{
				"name": "bone23",
				"parent": "bone4",
				"pivot": [0, 6.344, 6.344],
				"rotation": [10, 0, 0],
				"cubes": [
					{"origin": [0.1586, 4.26629, 15.73001], "size": [0.6344, 5.3924, 0.6344], "uv": [62, 61]},
					{"origin": [-2.0618, 4.26629, 15.73001], "size": [0.6344, 5.3924, 0.6344], "uv": [62, 61]},
					{"origin": [0.1586, 7.59689, 14.61981], "size": [0.6344, 2.0618, 1.1102], "uv": [62, 61]},
					{"origin": [-2.0618, 7.59689, 14.61981], "size": [0.6344, 2.0618, 1.1102], "uv": [62, 61]},
					{"origin": [-2.379, 1.45353, 16.58218], "size": [0.9516, 2.0618, 1.1102], "uv": [10, 55]},
					{"origin": [-2.0618, 4.54168, 14.3267], "size": [0.4758, 2.2204, 0.4758], "uv": [62, 61]},
					{"origin": [0.3172, 4.54168, 14.3267], "size": [0.4758, 2.2204, 0.4758], "uv": [62, 61]},
					{"origin": [0.3172, 4.34852, 12.68218], "size": [0.4758, 2.2204, 0.4758], "uv": [62, 61]},
					{"origin": [-2.0618, 4.34852, 12.68218], "size": [0.4758, 2.2204, 0.4758], "uv": [62, 61]},
					{"origin": [0.3172, 3.99916, 11.0101], "size": [0.4758, 2.2204, 0.4758], "uv": [62, 61]},
					{"origin": [-2.0618, 3.99916, 11.0101], "size": [0.4758, 2.2204, 0.4758], "uv": [62, 61]},
					{"origin": [0.1586, 1.45353, 16.58218], "size": [0.9516, 2.0618, 1.1102], "uv": [16, 52]}
				]
			},
			{
				"name": "bone24",
				"parent": "bone4",
				"pivot": [0, 6.344, 6.344],
				"rotation": [-20, 0, 0],
				"cubes": [
					{"origin": [-2.2204, 3, 5.586], "size": [3.172, 5.758, 3.8064], "uv": [0, 0], "inflate": 0.001}
				]
			},
			{
				"name": "bone25",
				"parent": "bone4",
				"pivot": [0, 6.344, 6.344],
				"rotation": [-30, 0, 0],
				"cubes": [
					{"origin": [-5.7096, 3, -5.516], "size": [9.516, 10.102, 11.102], "uv": [0, 4]},
					{"origin": [-4.1236, 2.68828, 4.89772], "size": [6.344, 9.4542, 1.586], "uv": [3, 5]}
				]
			}
		]
	}
}