
{
  "format_version": "1.8.0",
  "render_controllers": {
    "controller.render.ice_deinonychus": {
      "arrays": {
        "textures": {
          "Array.skins": [
            "Texture.numero0",
            "Texture.numero1",
            "Texture.numero2"
          ]
        }
      },
      "geometry": "Geometry.default",
      "part_visibility": [ 
        { "*": true },
        { "bono27": "query.variant == 2 || query.variant == 1"},
        { "leg11": "query.variant == 2 || query.variant == 1"},
        { "bone11": "query.variant == 2 || query.variant == 1"},
        { "bono28": "query.variant == 2 || query.variant == 1"},
        { "bono36": "query.variant == 2 || query.variant == 1"},
        { "bono35": "query.variant == 2 || query.variant == 1"},
        { "bono37": "query.variant == 2 || query.variant == 1"},
        { "bono38": "query.variant == 2 || query.variant == 1"},
        { "bono34": "query.variant == 2 || query.variant == 1"},
        { "bono33": "query.variant == 2 || query.variant == 1"},
        { "bono29": "query.variant == 2 || query.variant == 1"},
        { "bono30": "query.variant == 2 || query.variant == 1"},
        { "bono31": "query.variant == 2 || query.variant == 1"},
        { "bono32": "query.variant == 2 || query.variant == 1"},
        { "bono3": "query.variant == 2 || query.variant == 1"},
        { "bono6": "query.variant == 2 || query.variant == 1"},
        { "bone31": "query.variant == 2 || query.variant == 1"},
        { "bone30": "query.variant == 2 || query.variant == 1"},
        { "bono41": "query.variant == 2 || query.variant == 1"},
        { "bono42": "query.variant == 2 || query.variant == 1"},
        { "cola": "query.variant == 2 || query.variant == 1"},
        { "cuello1": "query.variant == 2 || query.variant == 1"},
        { "body": "query.variant == 2 || query.variant == 1"},
        { "bono43": "query.variant == 2 || query.variant == 1"},
        { "bono5": "query.variant == 2 || query.variant == 1"},
        { "bono2": "query.variant == 2 || query.variant == 1"},
        { "bono44": "query.variant == 2 || query.variant == 1"},
        { "leg3": "query.variant == 2 || query.variant == 1"},
        { "bone12": "query.variant == 2 || query.variant == 1"},
        { "bone13": "query.variant == 2 || query.variant == 1"},
        { "bone5": "query.variant == 2 || query.variant == 1"},
        { "bone21": "query.variant == 2 || query.variant == 1"},
        { "leg13": "query.variant == 2 || query.variant == 1"},
        { "bone20": "query.variant == 2 || query.variant == 1"},
     { "bone31": "query.variant == 2 || query.variant == 1"},
     { "bone30": "query.variant == 2 || query.variant == 1"},


        { "bono39": "query.variant == 2" },
        { "bono40": "query.variant == 2" },
        { "bone7": "query.variant == 2" },
        { "leg18": "query.variant == 2" },
        { "leg12": "query.variant == 2" },
        { "bone10": "query.variant == 2" },
        { "bone40": "query.variant == 2" },
        { "bone39": "query.variant == 2" },
        { "bono13": "query.variant == 2" },
        { "bone4": "query.variant == 2" },
        { "bone3": "query.variant == 2" },
        { "bone6": "query.variant == 2" },
        { "bone8": "query.variant == 2" },
        { "bono14": "query.variant == 2" },
        { "bone9": "query.variant == 2" },
        { "bono11": "query.variant == 2" },
        { "bono12": "query.variant == 2" },
        { "bono10": "query.variant == 2" },
        { "bono9": "query.variant == 2" },
        { "bone": "query.variant == 2" },
        { "bone2": "query.variant == 2" },
        { "egg": "query.variant == 0"},


 { "head*": "!(query.is_saddled || query.variant == 0)" },
 { "head2*": "!(query.is_saddled || query.variant == 0)" },
 { "bocabaja*": "!(query.is_saddled || query.variant == 0)" },
 { "bone16*": "!(query.is_saddled || query.variant == 0)" },
 { "bone15*": "!(query.is_saddled || query.variant == 0)" },
 { "bone14*": "!(query.is_saddled || query.variant == 0)" },
 { "bone18*": "!(query.is_saddled || query.variant == 0)" },
 { "bocaarriba*": "!(query.is_saddled || query.variant == 0)" },
 { "bono15*": "!(query.is_saddled || query.variant == 0 || query.variant == 1 )" },
 { "bone19*": "!(query.is_saddled || query.variant == 0 || query.variant == 1 )" },
 { "bone29*": "query.is_saddled"},
 { "montura2*": "query.is_saddled"},
 { "montura*": "query.is_saddled"},
 { "head3*": "query.is_saddled"},
 { "head4*": "query.is_saddled"},
 { "bocabaja2*": "query.is_saddled"},
 { "bone22*": "query.is_saddled"},
 { "bone32*": "query.is_saddled"},
 { "bocaarriba2*": "query.is_saddled"},
 { "bone25*": "query.is_saddled"},
 { "bone26*": "query.is_saddled"},
 { "bono17*": "query.is_saddled"},
 { "bono18*": "query.is_saddled"},
 { "bono19*": "query.is_saddled"},
 { "bono20*": "query.is_saddled"},
 { "bone27*": "query.is_saddled"},
 { "bone28*": "query.is_saddled"},
 { "bone24*": "query.is_saddled"},
 { "head28*": "query.is_saddled"},

 { "cofre*": "query.mark_variant == 1"}
      ],
      "materials": [ { "*": "Material.default"}
    ],
      "textures": [ "Array.skins[query.variant]" ]
    }
  }
}
